lapjv.cpython-39-x86_64-linux-gnu.so
lapjv-1.3.27.dist-info/LICENSE
lapjv-1.3.27.dist-info/WHEEL
lapjv-1.3.27.dist-info/top_level.txt
lapjv-1.3.27.dist-info/RECORD
lapjv-1.3.27.dist-info/METADATA
