Metadata-Version: 2.1
Name: lapjv
Version: 1.3.27
Summary: Linear sum assignment problem solver using Jonker-Volgenant algorithm.
Home-page: https://github.com/src-d/lapjv
Download-URL: https://github.com/src-d/lapjv
Author: Vadim Markovtsev
Author-email: gmarkhor@gmail.com
License: MIT
Classifier: Development Status :: 5 - Production/Stable
Classifier: Intended Audience :: Developers
Classifier: License :: OSI Approved :: MIT License
Classifier: Operating System :: POSIX :: Linux
Classifier: Topic :: Scientific/Engineering :: Information Analysis
Classifier: Programming Language :: Python :: 3.8
Classifier: Programming Language :: Python :: 3.9
Classifier: Programming Language :: Python :: 3.10
Classifier: Programming Language :: Python :: 3.11
License-File: LICENSE
Requires-Dist: numpy >=1.20.0
